{"moonrise": "01:09  DT", "event_type": "Unsolved & Mysterious Events", "apparition_type": "Spirit, Ghost", "year": "2022", "moon_upper_transit": "07:07  DT", "longitude_x": "-71.2426079", "fracillum": "44%", "country": "United States", "change_in_number_of_representatives": "", "state.1": "MA", "timezone": "-5.0", "personal theft/larceny": "12.0", "id": "10cf8445-b2a0-420b-affc-96e5aaea8101", "sunrise": "05:08  DT", "inflation adjusted cost": "7607000000.0", "city": "Tewksbury", "top 25% monthly binges": "3.6", "annual deaths (excessive alcohol)": "2760.0", "end_civil_twilight": "20:59  DT", "city_sunset": "", "geography_type": "", "city_x": "Tewksbury", "years of potential life lost": "71022.0", "audio_evidence": "True", "average_apportionment_population_per_representative": "", "state": "Massachusetts", "sun_upper_transit": "12:46  DT", "latitude": "42.6020617", "top 25% median drinks per binge": "7.0", "death rate increase (%)": "57.2", "death rate per capita": "2547.0", "aggravated assault": "141.0", "under 21 death percentage": "1.88", "jaccard_score": 0.0007907725029313119, "number_of_representatives": "", "description": "There are plenty of reports of doors opening and closing on their own, strange noises, and moving objects. Many sightings have occurred late at night near the cafeteria, formerly the gym. This is caused by the lingering spirit of a cheerleader who died during a competition there. There is a cheerleading award named after her as well. In the D-hall corridor, the heating pipes move spontaneously, and make quite a ruckus. When passing by the cafeteria, many people have gotten cold sweats, chills, and other sorts of strange feelings.", "cost per drink (in 2022 us$)": "2.61", "longitude_y": "-71.0589", "state_abbrev": "MA", "city_latitude": "42.6106478", "begin_civil_twilight": "04:33  DT", "resident_population": "", "state_y": "MA", "state_x": "Massachusetts", "median drinks per binge": "5.4", "number_of_tribes": "2.0", "resident_population_density_rank": "", "adult_35plus death percentage": "84.4", "percent_change_in_resident_population": "", "simple assault": "306.0", "male death percentage": "68.4", "latitude_x": "42.6020617", "resident_population_density": "", "usgs_region": "Northwest", "curphase": "Waning Crescent", "city_sunrise": "", "taxpayer cost": "5635000000.0", "hp_day": "2022/07/31", "moonset": "13:16  DT", "visual_evidence": "False", "witness_count": "1", "location": "Tewksbury Memorial High School", "longitude": "-71.2426079", "latitude_y": "42.3601", "time_of_day": "Night", "binge drinking (%)": "21.1", "sunset": "20:25  DT", "median binges monthly": "1.5", "percentage_of_total_tribes": "0.3780718336483932", "city_longitude": "-71.23422479999999", "quarter": "3", "chronic death percentage": "59.3", "rape/sexual assault": "42.0", "robbery": "48.0"}