{"moonrise": "02:12  DT", "event_type": "Unknown", "apparition_type": "Unknown", "year": "1976", "moon_upper_transit": "08:57  DT", "longitude_x": "-83.9638155", "fracillum": "30%", "change_in_number_of_representatives": "0.0", "median drinks per binge": "5.6", "number_of_representatives": "19.0", "timezone": "-5.0", "personal theft/larceny": "", "id": "1b59233f-3c4e-4f71-86ae-43330788e251", "sunrise": "06:00  DT", "inflation adjusted cost": "11018000000.0", "city": "Saginaw", "top 25% monthly binges": "4.3", "annual deaths (excessive alcohol)": "4548.0", "end_civil_twilight": "21:55  DT", "city_sunset": "6:25 pm \u2191 (261\u00b0)", "geography_type": "State", "city_x": "Saginaw", "years of potential life lost": "115890.0", "audio_evidence": "False", "average_apportionment_population_per_representative": "470379.0", "state": "Michigan", "state.1": "MI", "male death percentage": "67.9", "latitude": "43.4163816", "top 25% median drinks per binge": "7.9", "death rate increase (%)": "40.2", "death rate per capita": "2216.0", "location": "JB Meinburg's", "under 21 death percentage": "2.57", "jaccard_score": 0.0008180405202737709, "description": "JB Meinburg's is an old pub that is said to be haunted by an old bar maid. She occasionally is seen checking on the tables at the back of the bar. She has whispered in people's ears, asking if they needed a drink. She has been seen walking into the back hall. This bar is featured in our local paper just about every Halloween. I have only been to the bar once.", "cost per drink (in 2022 us$)": "2.84", "longitude_y": "-84.5555", "aggravated assault": "", "percentage_of_total_tribes": "2.2684310018903595", "resident_population": "8875083.0", "begin_civil_twilight": "05:25  DT", "city_latitude": "43.4194699", "state_y": "MI", "state_x": "Michigan", "state_abbrev": "MI", "binge drinking (%)": "19.8", "resident_population_density_rank": "13.0", "adult_35plus death percentage": "84.44", "percent_change_in_resident_population": "13.4", "simple assault": "", "sun_upper_transit": "13:40  DT", "latitude_x": "43.4163816", "resident_population_density": "157.0", "usgs_region": "Midwest", "quarter": "4", "city_sunrise": "5:36 am", "taxpayer cost": "8162000000.0", "hp_day": "1976/10/31", "moonset": "15:51  DT", "visual_evidence": "False", "witness_count": "1", "latitude_y": "42.7335", "longitude": "-83.9638155", "time_of_day": "Unknown", "number_of_tribes": "12.0", "sunset": "21:20  DT", "median binges monthly": "1.8", "country": "United States", "city_longitude": "-83.9508068", "curphase": "Waning Crescent", "chronic death percentage": "59.6", "rape/sexual assault": "", "robbery": ""}