{"moonrise": "02:55  DT", "event_type": "Unknown", "apparition_type": "Ghost", "state.1": "", "longitude_y": "-97.7431", "longitude_x": "-98.468016", "fracillum": "19%", "change_in_number_of_representatives": "", "year": "2025", "timezone": "-6.0", "personal theft/larceny": "", "id": "46256170-e9f9-4a85-ab04-d0ef5c952011", "death rate per capita": "2737.0", "inflation adjusted cost": "25408000000.0", "city": "San Antonio", "male death percentage": "71.1", "top 25% monthly binges": "4.1", "annual deaths (excessive alcohol)": "10647.0", "end_civil_twilight": "21:03  DT", "city_sunset": "", "geography_type": "", "city_x": "San Antonio", "years of potential life lost": "274633.0", "audio_evidence": "False", "average_apportionment_population_per_representative": "", "state": "Texas", "sunrise": "06:30  DT", "latitude": "29.33893789999999", "top 25% median drinks per binge": "9.0", "death rate increase (%)": "44.2", "location": "Stinson Field Cemetery and the Stinson Field ghost", "resident_population_density": "", "jaccard_score": 0.0006680664248902462, "quarter": "1", "number_of_representatives": "", "description": "It is said that the cemetery next to Stinson Municipal Airport (formerly Stinson Field) is haunted by blue lights over certain graves at night, which are in fact visible from the road when you're driving by. One of the old hangars at the Airport itself is also haunted, presumably by a man who was killed while starting his plane... though it's a condemned hangar used for long term storage only. Both of these, interestingly enough, are on the way to the Ghost Tracks of Shane and Villamin roads..", "cost per drink (in 2022 us$)": "2.69", "moon_upper_transit": "09:48  DT", "aggravated assault": "", "percentage_of_total_tribes": "", "city_latitude": "29.4241219", "begin_civil_twilight": "06:02  DT", "resident_population": "", "state_y": "", "state_x": "Texas", "median drinks per binge": "5.6", "number_of_tribes": "", "resident_population_density_rank": "", "adult_35plus death percentage": "81.9", "percent_change_in_resident_population": "", "simple assault": "", "latitude_y": "30.2672", "latitude_x": "29.33893789999999", "under 21 death percentage": "3.97", "usgs_region": "", "sun_upper_transit": "13:33  DT", "city_sunrise": "", "taxpayer cost": "18821000000.0", "country": "United States", "moonset": "16:49  DT", "visual_evidence": "False", "witness_count": "2", "state_abbrev": "TX", "longitude": "-98.468016", "time_of_day": "Night", "binge drinking (%)": "17.6", "sunset": "20:36  DT", "median binges monthly": "1.8", "hp_day": "2025/01/01", "city_longitude": "-98.4936282", "curphase": "Waning Crescent", "chronic death percentage": "56.9", "rape/sexual assault": "", "robbery": ""}