{"moonrise": "02:18  DT", "event_type": "Unsolved & Mysterious Events", "apparition_type": "Unknown", "state.1": "IA", "longitude_y": "-93.6208", "longitude_x": "", "fracillum": "19%", "change_in_number_of_representatives": "", "year": "2025", "timezone": "-6.0", "personal theft/larceny": "", "id": "b6b3c601-f106-4b74-9c65-36b524cb267d", "sunrise": "05:41  DT", "inflation adjusted cost": "2610000000.0", "city": "Laurens", "top 25% monthly binges": "4.3", "annual deaths (excessive alcohol)": "1305.0", "end_civil_twilight": "21:26  DT", "city_sunset": "", "geography_type": "", "city_x": "Laurens", "years of potential life lost": "30070.0", "audio_evidence": "True", "average_apportionment_population_per_representative": "", "state": "Iowa", "male death percentage": "69.4", "latitude": "", "top 25% median drinks per binge": "9.2", "death rate increase (%)": "51.8", "death rate per capita": "2445.0", "aggravated assault": "", "resident_population_density": "", "jaccard_score": 0.0006680664248902462, "quarter": "1", "number_of_representatives": "", "description": "out in the middle of the country you will go up a hill on a gravel road. On top of that hill you will see an old run down white abandon house. To your left pushed back in the corner of A lot of trees you will see a small cemetery. No one has been buried here in years, and as you walk into the graveyard you will see to your left 3 small graves with the same last name. Legend has it that the three graves are from 3 little girls that lived in the house a long time ago until there father killed them. Some people went into the house and found a bunch of old toys and stuffed animals. Gusts of cold wind will blow as soon as you step out of your car, and many voices have been heard inside the small round cemetery.", "cost per drink (in 2022 us$)": "2.15", "moon_upper_transit": "09:31  DT", "percentage_of_total_tribes": "0.1890359168241966", "state_abbrev": "IA", "resident_population": "", "begin_civil_twilight": "05:06  DT", "city_latitude": "42.8466398", "state_y": "IA", "state_x": "Iowa", "median drinks per binge": "5.8", "binge drinking (%)": "24.5", "resident_population_density_rank": "", "adult_35plus death percentage": "88.0", "percent_change_in_resident_population": "", "simple assault": "", "latitude_y": "41.5908", "latitude_x": "", "under 21 death percentage": "2.45", "usgs_region": "Midwest", "sun_upper_transit": "13:16  DT", "city_sunrise": "", "taxpayer cost": "1934000000.0", "country": "United States", "moonset": "16:58  DT", "visual_evidence": "True", "witness_count": "3", "location": "infant cemetery", "longitude": "", "time_of_day": "Unknown", "number_of_tribes": "1.0", "sunset": "20:52  DT", "median binges monthly": "1.9", "hp_day": "2025/01/01", "city_longitude": "-94.8519296", "curphase": "Waning Crescent", "chronic death percentage": "67.0", "rape/sexual assault": "", "robbery": ""}