{"moonrise": "02:10  DT", "event_type": "Unsolved & Mysterious Events", "apparition_type": "Spirit, Demonic Entity, Extraterrestrial", "year": "2025", "moon_upper_transit": "09:33  DT", "longitude_x": "-123.0850834", "fracillum": "18%", "change_in_number_of_representatives": "", "state.1": "OR", "timezone": "-8.0", "personal theft/larceny": "", "id": "c9732539-5764-405c-a3ab-eb871d3ba635", "death rate per capita": "1938.0", "inflation adjusted cost": "4752000000.0", "city": "Gold Hill", "top 25% monthly binges": "4.1", "visual_evidence": "False", "end_civil_twilight": "21:40  DT", "city_sunset": "", "geography_type": "", "city_x": "Gold Hill", "years of potential life lost": "50830.0", "audio_evidence": "False", "average_apportionment_population_per_representative": "", "state": "Oregon", "male death percentage": "68.1", "latitude": "42.4930046", "top 25% median drinks per binge": "7.4", "death rate increase (%)": "44.2", "location": "(Near) Oregon Vortex", "under 21 death percentage": "1.97", "jaccard_score": 0.0006953344422327052, "number_of_representatives": "", "description": "Several visitors to the vortex have seen John Lister, the Scottish scientist who discovered the area, standing at the top of the sloping floor of the old log cabin. He is usually seen resting against the wall, laughing and plucking his eyebrow. The visitors have asked the guide the identity of the man who somehow got ahead of the tour. One tour guide looked inside and recognized Lister from an old photograph. After the quick look, Lister disappeared. When the other tour guides looked inside the cabin, there was no one there. Anyone leaving the cabin by the back door would have been seen. Also, Native American legend says that horses would not come into the affected area known as the \"Forbidden Ground.\"", "cost per drink (in 2022 us$)": "2.81", "longitude_y": "-123.0351", "aggravated assault": "", "percentage_of_total_tribes": "1.1342155009451798", "state_abbrev": "OR", "city_latitude": "42.4317894", "begin_civil_twilight": "04:48  DT", "resident_population": "", "state_y": "OR", "sunrise": "05:26  DT", "median drinks per binge": "5.5", "binge drinking (%)": "17.0", "resident_population_density_rank": "", "adult_35plus death percentage": "89.3", "percent_change_in_resident_population": "", "simple assault": "", "sun_upper_transit": "13:14  DT", "latitude_x": "42.4930046", "resident_population_density": "", "median binges monthly": "1.7", "usgs_region": "Northwest", "quarter": "1", "city_sunrise": "", "state_x": "Oregon", "taxpayer cost": "3520000000.0", "country": "United States", "moonset": "17:12  DT", "annual deaths (excessive alcohol)": "2186.0", "witness_count": "1", "latitude_y": "44.9429", "longitude": "-123.0850834", "time_of_day": "Unknown", "number_of_tribes": "6.0", "sunset": "21:02  DT", "robbery": "", "hp_day": "2025/01/01", "city_longitude": "-123.0506035", "curphase": "Waning Crescent", "chronic death percentage": "68.3", "rape/sexual assault": ""}