{"moonrise": "02:18  DT", "event_type": "Unknown", "apparition_type": "Spirit, Ghost", "year": "2025", "longitude_y": "-93.6208", "longitude_x": "-93.6464654", "fracillum": "19%", "change_in_number_of_representatives": "", "state.1": "IA", "timezone": "-6.0", "personal theft/larceny": "", "id": "f60ff18e-6e51-4107-a1d1-e141290660ca", "death rate per capita": "2445.0", "inflation adjusted cost": "2610000000.0", "city": "Ames", "top 25% monthly binges": "4.3", "annual deaths (excessive alcohol)": "1305.0", "end_civil_twilight": "21:26  DT", "city_sunset": "6:05 pm \u2191 (261\u00b0)", "geography_type": "", "city_x": "Ames", "years of potential life lost": "30070.0", "audio_evidence": "True", "average_apportionment_population_per_representative": "", "state": "Iowa", "male death percentage": "69.4", "latitude": "42.0266187", "top 25% median drinks per binge": "9.2", "death rate increase (%)": "51.8", "aggravated assault": "", "resident_population_density": "", "jaccard_score": 0.0007226024595751643, "quarter": "1", "number_of_representatives": "", "description": "C. Y. Stephens Auditorium - The auditorium is haunted by the benevolent ghost of C. Y. Stephens. He is especially present in the basement tunnels that run between the auditorium and the coliseum and Fisher Building. Cold drafts and footsteps are among the ways he makes himself known. He can also be seen from the stage sitting in the back right corner of the third balcony whenever the house lights are on and the stage lights are low. His presence is thought of, at least by dancers in the annual Nutcracker production, to be a sign of good luck for the performance.", "cost per drink (in 2022 us$)": "2.15", "moon_upper_transit": "09:31  DT", "percentage_of_total_tribes": "0.1890359168241966", "state_abbrev": "IA", "resident_population": "", "begin_civil_twilight": "05:06  DT", "city_latitude": "42.0307812", "state_y": "IA", "sunrise": "05:41  DT", "median drinks per binge": "5.8", "binge drinking (%)": "24.5", "resident_population_density_rank": "", "adult_35plus death percentage": "88.0", "percent_change_in_resident_population": "", "simple assault": "", "latitude_y": "41.5908", "latitude_x": "42.0266187", "under 21 death percentage": "2.45", "usgs_region": "Midwest", "sun_upper_transit": "13:16  DT", "city_sunrise": "5:16 am", "state_x": "Iowa", "taxpayer cost": "1934000000.0", "country": "United States", "moonset": "16:58  DT", "visual_evidence": "False", "witness_count": "1", "location": "Iowa State University", "longitude": "-93.6464654", "time_of_day": "Unknown", "number_of_tribes": "1.0", "sunset": "20:52  DT", "median binges monthly": "1.9", "hp_day": "2025/01/01", "city_longitude": "-93.6319131", "curphase": "Waning Crescent", "chronic death percentage": "67.0", "rape/sexual assault": "", "robbery": ""}