{"moonrise": "02:04  DT", "event_type": "Unknown", "apparition_type": "Unknown", "number_of_representatives": "", "moon_upper_transit": "09:12  DT", "longitude_x": "-75.307326", "fracillum": "19%", "change_in_number_of_representatives": "", "median drinks per binge": "5.2", "year": "2025", "timezone": "-5.0", "personal theft/larceny": "", "id": "df696bb9-c791-48bb-beca-a11f5ea91d6c", "sunrise": "05:30  DT", "inflation adjusted cost": "8337000000.0", "city": "Swedesboro", "top 25% monthly binges": "3.5", "annual deaths (excessive alcohol)": "3008.0", "end_civil_twilight": "21:05  DT", "city_sunset": "", "geography_type": "", "city_x": "Swedesboro", "years of potential life lost": "79359.0", "audio_evidence": "True", "average_apportionment_population_per_representative": "", "state": "New Jersey", "state.1": "NJ", "location": "Swedesboro Lake", "latitude": "39.7434488", "top 25% median drinks per binge": "7.3", "death rate increase (%)": "42.8", "death rate per capita": "3088.0", "aggravated assault": "", "resident_population_density": "", "jaccard_score": 0.0006817004335614757, "quarter": "1", "description": "Reported sightings of a man on a bike as well as screaming.", "cost per drink (in 2022 us$)": "2.3", "longitude_y": "-74.7691", "percentage_of_total_tribes": "0.1890359168241966", "city_latitude": "39.7476136", "begin_civil_twilight": "04:57  DT", "resident_population": "", "state_y": "NJ", "state_x": "New Jersey", "state_abbrev": "NJ", "binge drinking (%)": "14.4", "resident_population_density_rank": "", "adult_35plus death percentage": "82.6", "percent_change_in_resident_population": "", "simple assault": "", "male death percentage": "34.0", "latitude_x": "39.7434488", "under 21 death percentage": "2.23", "median binges monthly": "", "usgs_region": "Northeast", "sun_upper_transit": "13:01  DT", "city_sunrise": "", "taxpayer cost": "6175000000.0", "country": "United States", "moonset": "16:35  DT", "visual_evidence": "False", "witness_count": "2", "latitude_y": "40.2206", "longitude": "-75.307326", "time_of_day": "Unknown", "number_of_tribes": "1.0", "sunset": "20:32  DT", "robbery": "", "hp_day": "2025/01/01", "city_longitude": "-75.3104654", "curphase": "Waning Crescent", "chronic death percentage": "54.8", "rape/sexual assault": ""}