{"moonrise": "02:20  DT", "event_type": "Unknown", "apparition_type": "Ghost", "state.1": "", "longitude_y": "-105.9394", "longitude_x": "-106.639201", "fracillum": "18%", "change_in_number_of_representatives": "", "year": "2025", "timezone": "-7.0", "personal theft/larceny": "", "id": "87200aa1-073a-43ec-b47f-d437e094c818", "sunrise": "05:48  DT", "inflation adjusted cost": "3014000000.0", "city": "Albuquerque", "top 25% monthly binges": "4.5", "annual deaths (excessive alcohol)": "1581.0", "end_civil_twilight": "20:53  DT", "city_sunset": "6:02 pm \u2191 (262\u00b0)", "geography_type": "", "city_x": "Albuquerque", "years of potential life lost": "45047.0", "audio_evidence": "False", "average_apportionment_population_per_representative": "", "state": "New Mexico", "death rate per capita": "1339.0", "latitude": "35.08162799999999", "top 25% median drinks per binge": "7.9", "death rate increase (%)": "36.0", "location": "Albuquerque Press Club", "under 21 death percentage": "2.59", "jaccard_score": 0.0006680664248902462, "quarter": "1", "number_of_representatives": "", "description": "the ghost of \"Mrs. M\" appears at the bar.", "cost per drink (in 2022 us$)": "3.74", "moon_upper_transit": "09:22  DT", "aggravated assault": "", "percentage_of_total_tribes": "", "state_abbrev": "NM", "resident_population": "", "begin_civil_twilight": "05:18  DT", "city_latitude": "35.0853336", "state_y": "", "state_x": "New Mexico", "median drinks per binge": "5.5", "number_of_tribes": "", "resident_population_density_rank": "", "adult_35plus death percentage": "81.6", "percent_change_in_resident_population": "", "simple assault": "", "male death percentage": "70.6", "latitude_x": "35.08162799999999", "resident_population_density": "", "median binges monthly": "1.8", "usgs_region": "", "sun_upper_transit": "13:06  DT", "city_sunrise": "5:11 am", "taxpayer cost": "2233000000.0", "country": "United States", "moonset": "16:35  DT", "visual_evidence": "False", "witness_count": "1", "latitude_y": "35.6822", "longitude": "-106.639201", "time_of_day": "Unknown", "binge drinking (%)": "15.6", "sunset": "20:23  DT", "robbery": "", "hp_day": "2025/01/01", "city_longitude": "-106.6055534", "curphase": "Waning Crescent", "chronic death percentage": "61.2", "rape/sexual assault": ""}