{"moonrise": "12:33  DT", "event_type": "Paranormal & Supernatural Deaths", "apparition_type": "Misty Figure, Ghost", "state.1": "WA", "moon_upper_transit": "18:52  DT", "longitude_x": "-119.3215697", "fracillum": "43%", "country": "United States", "change_in_number_of_representatives": "0.0", "year": "2007", "timezone": "-8.0", "personal theft/larceny": "17.0", "id": "2d1c052b-6dd5-4733-98ae-5108f9646ed9", "sunrise": "05:16  DT", "inflation adjusted cost": "7837000000.0", "city": "Moses Lake", "top 25% monthly binges": "3.6", "annual deaths (excessive alcohol)": "3184.0", "end_civil_twilight": "21:50  DT", "city_sunset": "", "geography_type": "State", "city_x": "Moses Lake", "years of potential life lost": "77302.0", "audio_evidence": "True", "average_apportionment_population_per_representative": "656520.0", "state": "Washington", "latitude_y": "47.0379", "latitude": "47.1828499", "top 25% median drinks per binge": "6.8", "death rate increase (%)": "42.8", "death rate per capita": "2420.0", "aggravated assault": "82.0", "resident_population_density": "88.7", "jaccard_score": 0.0008725765549586889, "quarter": "2", "number_of_representatives": "9.0", "description": "This haunting has been described as mysterious noises that happen around 11:30 P.M., and also a smoke-like apparition with only the legs showing is seen running down the hallway. An alarm has also been heard. - April 2007 Update - that building was torn down in 2005 and now there is nothing there. Workers involved in the demolition claimed that when they took down decorations inside the classroom the next day they would be replaced as if they never touched them.", "cost per drink (in 2022 us$)": "3.01", "longitude_y": "-122.9007", "state_abbrev": "WA", "resident_population": "5894121.0", "begin_civil_twilight": "04:36  DT", "city_latitude": "47.1301417", "state_y": "WA", "state_x": "Washington", "median drinks per binge": "5.3", "binge drinking (%)": "15.4", "resident_population_density_rank": "27.0", "adult_35plus death percentage": "87.2", "percent_change_in_resident_population": "21.1", "simple assault": "278.0", "male death percentage": "66.0", "latitude_x": "47.1828499", "under 21 death percentage": "1.82", "usgs_region": "Northwest", "sun_upper_transit": "13:13  DT", "city_sunrise": "", "taxpayer cost": "5805000000.0", "hp_day": "2007/04/20", "moonset": "00:44  DT", "visual_evidence": "True", "witness_count": "3", "location": "Columbia Basin Alternative High School", "longitude": "-119.3215697", "time_of_day": "Unknown", "number_of_tribes": "30.0", "sunset": "21:10  DT", "median binges monthly": "1.5", "percentage_of_total_tribes": "5.671077504725898", "city_longitude": "-119.2780771", "curphase": "Waxing Crescent", "chronic death percentage": "64.6", "rape/sexual assault": "17.0", "robbery": "54.0"}