{"moonrise": "01:17  DT", "event_type": "Torture & Extreme Crimes, Violent Deaths", "apparition_type": "Spirit", "state.1": "MA", "moon_upper_transit": "08:02  DT", "longitude_x": "-72.5568064", "fracillum": "30%", "country": "United States", "change_in_number_of_representatives": "0.0", "year": "1976", "timezone": "-5.0", "personal theft/larceny": "", "id": "7140cf51-3a2c-48ce-b174-9abf2746a542", "sunrise": "05:07  DT", "inflation adjusted cost": "7607000000.0", "city": "Turners Falls", "top 25% monthly binges": "3.6", "annual deaths (excessive alcohol)": "2760.0", "end_civil_twilight": "20:59  DT", "city_sunset": "", "geography_type": "State", "city_x": "Turners Falls", "years of potential life lost": "71022.0", "audio_evidence": "False", "average_apportionment_population_per_representative": "477223.0", "state": "Massachusetts", "male death percentage": "68.4", "latitude": "42.5997784", "top 25% median drinks per binge": "7.0", "death rate increase (%)": "57.2", "death rate per capita": "2547.0", "aggravated assault": "", "under 21 death percentage": "1.88", "jaccard_score": 0.0008180405202737709, "number_of_representatives": "12.0", "description": "A man was burnt alive in the school and haunts the new foundation. He doesn't harm anyone. But he scare's people with horrible vision's of a Clown stabbing himself with a knife. Or doing other horrible things.", "cost per drink (in 2022 us$)": "2.61", "longitude_y": "-71.0589", "state_abbrev": "MA", "resident_population": "5689170.0", "begin_civil_twilight": "04:33  DT", "city_latitude": "42.60425230000001", "state_y": "MA", "state_x": "Massachusetts", "median drinks per binge": "5.4", "number_of_tribes": "2.0", "resident_population_density_rank": "5.0", "adult_35plus death percentage": "84.4", "percent_change_in_resident_population": "10.5", "simple assault": "", "sun_upper_transit": "12:46  DT", "latitude_x": "42.5997784", "resident_population_density": "729.4", "usgs_region": "Northwest", "quarter": "4", "city_sunrise": "", "taxpayer cost": "5635000000.0", "hp_day": "1976/12/31", "moonset": "14:54  DT", "visual_evidence": "False", "witness_count": "1", "location": "Old Shefield", "longitude": "-72.5568064", "latitude_y": "42.3601", "time_of_day": "Unknown", "binge drinking (%)": "21.1", "sunset": "20:25  DT", "median binges monthly": "1.5", "percentage_of_total_tribes": "0.3780718336483932", "city_longitude": "-72.5564777", "curphase": "Waning Crescent", "chronic death percentage": "59.3", "rape/sexual assault": "", "robbery": ""}