{"moonrise": "23:37  DT", "event_type": "Unknown", "apparition_type": "Unknown", "year": "2008", "longitude_y": "-84.5555", "longitude_x": "-84.65071999999999", "fracillum": "92%", "change_in_number_of_representatives": "-1.0", "median drinks per binge": "5.6", "number_of_representatives": "15.0", "timezone": "-5.0", "personal theft/larceny": "6.0", "id": "809aa9f9-1dde-4b5c-80cb-a3a9be780d92", "death rate per capita": "2216.0", "inflation adjusted cost": "11018000000.0", "city": "Houghton Lake", "top 25% monthly binges": "4.3", "annual deaths (excessive alcohol)": "4548.0", "end_civil_twilight": "21:55  DT", "city_sunset": "", "geography_type": "State", "city_x": "Houghton Lake", "years of potential life lost": "115890.0", "audio_evidence": "False", "average_apportionment_population_per_representative": "663722.0", "state": "Michigan", "state.1": "MI", "sunrise": "06:00  DT", "latitude": "44.2988715", "top 25% median drinks per binge": "7.9", "death rate increase (%)": "40.2", "location": "Walgreen\u2019s", "resident_population_density": "175.8", "jaccard_score": 0.0008453085376162299, "description": "Formerly The Brass Lantern Restaurant - The Brass Inn is a very expensive restaurant. It has a bar as well, in the smoking section. The bar is haunted. Witness have seen a guy sitting in stool #2 from the left (NOT from the bar tenders point of view). Then he disappears. Sometimes there is a VERY EERIE feeling when you walk over to the bar. - March 2008 Update: Nothing has been reported since it was replaced by Walgreen\u2019s.", "cost per drink (in 2022 us$)": "2.84", "moon_upper_transit": "03:45  DT", "aggravated assault": "63.0", "percentage_of_total_tribes": "2.2684310018903595", "city_latitude": "44.314739", "begin_civil_twilight": "05:25  DT", "resident_population": "9938444.0", "state_y": "MI", "state_x": "Michigan", "state_abbrev": "MI", "binge drinking (%)": "19.8", "resident_population_density_rank": "17.0", "adult_35plus death percentage": "84.44", "percent_change_in_resident_population": "6.9", "simple assault": "218.0", "male death percentage": "67.9", "latitude_x": "44.2988715", "under 21 death percentage": "2.57", "median binges monthly": "1.8", "usgs_region": "Midwest", "sun_upper_transit": "13:40  DT", "city_sunrise": "", "taxpayer cost": "8162000000.0", "country": "United States", "moonset": "08:29  DT", "visual_evidence": "False", "witness_count": "1", "latitude_y": "42.7335", "longitude": "-84.65071999999999", "curphase": "Waning Gibbous", "time_of_day": "Unknown", "number_of_tribes": "12.0", "sunset": "21:20  DT", "robbery": "30.0", "hp_day": "2008/03/01", "city_longitude": "-84.7647496", "quarter": "1", "chronic death percentage": "59.6", "rape/sexual assault": "23.0"}