{"moonrise": "02:36  DT", "event_type": "Unsolved & Mysterious Events, Paranormal & Supernatural Deaths", "apparition_type": "Extraterrestrial", "state.1": "", "longitude_y": "-81.6326", "longitude_x": "-81.2409339", "fracillum": "19%", "change_in_number_of_representatives": "", "median drinks per binge": "6.4", "year": "2025", "timezone": "-5.0", "personal theft/larceny": "", "id": "814657c6-6ae6-4f70-9071-c5548eb0237a", "sunrise": "06:03  DT", "inflation adjusted cost": "1802000000.0", "city": "Raleigh County", "top 25% monthly binges": "5.1", "visual_evidence": "False", "end_civil_twilight": "21:25  DT", "city_sunset": "", "geography_type": "", "city_x": "Raleigh County", "years of potential life lost": "28285.0", "audio_evidence": "True", "average_apportionment_population_per_representative": "", "state": "West Virginia", "male death percentage": "70.8", "latitude": "37.6276151", "top 25% median drinks per binge": "9.8", "death rate increase (%)": "39.1", "death rate per capita": "1730.0", "aggravated assault": "", "under 21 death percentage": "2.03", "jaccard_score": 0.0006817004335614757, "quarter": "1", "number_of_representatives": "", "description": "Old Stoco Jr. High - Voices, footsteps, echoes, and people moving can be heard when walking through this school. Strange writings have appeared on the walls of witchcraft and unexplainable things. Unairing sense of eyes upon you wherever you go. Something paranormal is definitely happening there. Rumor has it one night during a game, someone pushed a boy who played basketball into the bleachers and he cracked his head open and died on the way to the hospital. You could still hear sounds of screeching tennis shoes on the gym floor, and you could hear him dribbling his ball down the court.", "cost per drink (in 2022 us$)": "2.97", "moon_upper_transit": "09:41  DT", "percentage_of_total_tribes": "", "city_latitude": "37.7381597", "begin_civil_twilight": "05:31  DT", "resident_population": "", "state_y": "", "state_x": "West Virginia", "state_abbrev": "WV", "binge drinking (%)": "13.9", "resident_population_density_rank": "", "adult_35plus death percentage": "84.0", "percent_change_in_resident_population": "", "simple assault": "", "latitude_y": "38.3498", "latitude_x": "37.6276151", "resident_population_density": "", "median binges monthly": "1.8", "usgs_region": "", "sun_upper_transit": "13:28  DT", "city_sunrise": "", "taxpayer cost": "1335000000.0", "country": "United States", "moonset": "16:59  DT", "annual deaths (excessive alcohol)": "1037.0", "witness_count": "2", "location": "Besoco", "longitude": "-81.2409339", "time_of_day": "Night", "number_of_tribes": "", "sunset": "20:54  DT", "robbery": "", "hp_day": "2025/01/01", "city_longitude": "-81.2518833", "curphase": "Waning Crescent", "chronic death percentage": "49.8", "rape/sexual assault": ""}