{"moonrise": "02:08  DT", "event_type": "Accidents & Natural Disasters", "apparition_type": "Unknown", "state.1": "", "longitude_y": "-104.9903", "longitude_x": "-104.8504458", "fracillum": "18%", "change_in_number_of_representatives": "", "median drinks per binge": "5.6", "year": "2025", "timezone": "-7.0", "personal theft/larceny": "", "id": "26a155a0-c137-4062-84b4-46cdee6ab79c", "death rate per capita": "2201.0", "inflation adjusted cost": "6826000000.0", "city": "Colorado Springs", "top 25% monthly binges": "3.7", "visual_evidence": "False", "end_civil_twilight": "21:04  DT", "city_sunset": "", "geography_type": "", "city_x": "Colorado Springs", "years of potential life lost": "71300.0", "audio_evidence": "False", "average_apportionment_population_per_representative": "", "state": "Colorado", "sunrise": "05:32  DT", "latitude": "38.7910423", "top 25% median drinks per binge": "7.6", "death rate increase (%)": "45.4", "location": "Broadmoor Hotel", "resident_population_density": "", "jaccard_score": 0.0006680664248902462, "quarter": "1", "number_of_representatives": "", "description": "There was once a fire in this hotel. Guests have claimed to hear the ghosts of the fire victims. - February 2007 Correction: A former worker reports there never was a fire in the Broadmoor Hotel. However, that isn't to say that there aren\u2019t any ghosts. There are several stories in which employees late at night have seen a woman dressed in 1920s clothing walking around the main Hotel. It is believed that this lady is very likely the Countess Portales, wife of Count Portales who built the original casino which had been moved and then used as a golf club house before being torn down in the 1990s.", "cost per drink (in 2022 us$)": "2.89", "moon_upper_transit": "09:18  DT", "aggravated assault": "", "percentage_of_total_tribes": "", "city_latitude": "38.8338816", "begin_civil_twilight": "05:00  DT", "resident_population": "", "state_y": "", "state_x": "Colorado", "state_abbrev": "CO", "binge drinking (%)": "19.8", "resident_population_density_rank": "", "adult_35plus death percentage": "83.1", "percent_change_in_resident_population": "", "simple assault": "", "male death percentage": "67.7", "latitude_x": "38.7910423", "under 21 death percentage": "2.78", "median binges monthly": "1.6", "usgs_region": "", "sun_upper_transit": "13:02  DT", "city_sunrise": "", "taxpayer cost": "5057000000.0", "country": "United States", "moonset": "16:41  DT", "annual deaths (excessive alcohol)": "2623.0", "witness_count": "2", "latitude_y": "39.7392", "longitude": "-104.8504458", "time_of_day": "Night", "number_of_tribes": "", "sunset": "20:31  DT", "robbery": "", "hp_day": "2025/01/01", "city_longitude": "-104.8213634", "curphase": "Waning Crescent", "chronic death percentage": "61.3", "rape/sexual assault": ""}