{"moonrise": "02:10  DT", "event_type": "Unknown", "apparition_type": "Spirit, Demonic Entity, Ghost", "year": "2025", "longitude_y": "-123.0351", "longitude_x": "-123.0097436", "fracillum": "18%", "change_in_number_of_representatives": "", "state.1": "OR", "timezone": "-8.0", "personal theft/larceny": "", "id": "174bce97-2434-4bd1-9b92-be50226b0a5d", "death rate per capita": "1938.0", "inflation adjusted cost": "4752000000.0", "city": "Jacksonville", "top 25% monthly binges": "4.1", "visual_evidence": "False", "end_civil_twilight": "21:40  DT", "city_sunset": "6:25 pm \u2191 (262\u00b0)", "geography_type": "", "city_x": "Jacksonville", "years of potential life lost": "50830.0", "audio_evidence": "True", "average_apportionment_population_per_representative": "", "state": "Oregon", "male death percentage": "68.1", "latitude": "42.3031964", "top 25% median drinks per binge": "7.4", "death rate increase (%)": "44.2", "location": "Wagon Trail Road", "under 21 death percentage": "1.97", "jaccard_score": 0.0007362364682463938, "number_of_representatives": "", "description": "Cupboards opening and slamming shut, Doors open and shut, Animals going insane, Evil presence, Beating on homes on all sides at the same time, Lights in homes, Footsteps on the hill(no one was there), Voices, Something touched a witness\u2019s wife\u2019s side,", "cost per drink (in 2022 us$)": "2.81", "moon_upper_transit": "09:33  DT", "aggravated assault": "", "percentage_of_total_tribes": "1.1342155009451798", "state_abbrev": "OR", "resident_population": "", "begin_civil_twilight": "04:48  DT", "city_latitude": "42.31345839999999", "state_y": "OR", "sunrise": "05:26  DT", "median drinks per binge": "5.5", "binge drinking (%)": "17.0", "resident_population_density_rank": "", "adult_35plus death percentage": "89.3", "percent_change_in_resident_population": "", "simple assault": "", "sun_upper_transit": "13:14  DT", "latitude_x": "42.3031964", "resident_population_density": "", "median binges monthly": "1.7", "usgs_region": "Northwest", "quarter": "1", "city_sunrise": "5:32 am", "state_x": "Oregon", "taxpayer cost": "3520000000.0", "country": "United States", "moonset": "17:12  DT", "annual deaths (excessive alcohol)": "2186.0", "witness_count": "8", "latitude_y": "44.9429", "longitude": "-123.0097436", "time_of_day": "Unknown", "number_of_tribes": "6.0", "sunset": "21:02  DT", "robbery": "", "hp_day": "2025/01/01", "city_longitude": "-122.9669865", "curphase": "Waning Crescent", "chronic death percentage": "68.3", "rape/sexual assault": ""}