{"moonrise": "14:20  ST", "event_type": "Unknown", "apparition_type": "Unknown", "year": "1885", "longitude_y": "-76.8867", "longitude_x": "-77.16306689999999", "fracillum": "72%", "change_in_number_of_representatives": "", "median drinks per binge": "5.5", "state.1": "", "timezone": "-5.0", "latitude_y": "40.2732", "id": "d6cd3f22-2d1b-4b95-b463-6f4d20770d82", "death rate per capita": "2280.0", "inflation adjusted cost": "12885000000.0", "city": "Carlisle", "top 25% monthly binges": "3.9", "visual_evidence": "False", "end_civil_twilight": "20:14  ST", "city_sunset": "", "geography_type": "", "city_x": "Carlisle", "years of potential life lost": "149637.0", "audio_evidence": "False", "average_apportionment_population_per_representative": "", "state": "Pennsylvania", "sunrise": "04:38  ST", "latitude": "40.2034861", "top 25% median drinks per binge": "7.9", "death rate increase (%)": "45.4", "aggravated assault": "", "resident_population_density": "", "jaccard_score": 0.0006271643988765577, "quarter": "3", "number_of_representatives": "", "description": "Letort View Community Center - At least three ghosts hunt this place. Most likely many more. From Jim Thorpe, A lady in a ball gown, a farmer and Native Americans from the Carlisle Indian School. The basement is so haunted they call it purgatory.", "cost per drink (in 2022 us$)": "2.59", "moon_upper_transit": "20:02  ST", "percentage_of_total_tribes": "", "city_latitude": "40.2010241", "begin_civil_twilight": "04:05  ST", "resident_population": "", "state_y": "", "state_x": "Pennsylvania", "state_abbrev": "PA", "number_of_tribes": "", "resident_population_density_rank": "", "adult_35plus death percentage": "81.7", "percent_change_in_resident_population": "", "simple assault": "", "male death percentage": "69.0", "latitude_x": "40.2034861", "under 21 death percentage": "2.67", "usgs_region": "", "sun_upper_transit": "12:09  ST", "city_sunrise": "", "taxpayer cost": "9544000000.0", "country": "United States", "moonset": "01:04  ST", "annual deaths (excessive alcohol)": "5703.0", "witness_count": "3", "location": "Carlisle Barracks", "longitude": "-77.16306689999999", "curphase": "Waxing Gibbous", "time_of_day": "Unknown", "binge drinking (%)": "18.5", "sunset": "19:41  ST", "median binges monthly": "1.8", "hp_day": "1885/07/13", "city_longitude": "-77.20027449999999", "personal theft/larceny": "", "chronic death percentage": "52.4", "rape/sexual assault": "", "robbery": ""}