{"moonrise": "04:42  ST", "event_type": "Unknown", "apparition_type": "Unknown", "state.1": "WI", "longitude_y": "-89.4012", "longitude_x": "-89.1458237", "fracillum": "0%", "change_in_number_of_representatives": "", "median drinks per binge": "5.5", "year": "1887", "timezone": "-6.0", "personal theft/larceny": "", "id": "a7339f4c-05ba-4e9e-a43b-145b78772610", "sunrise": "04:18  ST", "inflation adjusted cost": "6011000000.0", "city": "Antigo", "top 25% monthly binges": "3.8", "annual deaths (excessive alcohol)": "2651.0", "end_civil_twilight": "20:16  ST", "city_sunset": "", "geography_type": "", "city_x": "Antigo", "years of potential life lost": "64214.0", "audio_evidence": "False", "average_apportionment_population_per_representative": "", "state": "Wisconsin", "location": "McMillan hotel", "latitude": "45.1658267", "top 25% median drinks per binge": "7.5", "death rate increase (%)": "51.4", "death rate per capita": "2223.0", "aggravated assault": "", "under 21 death percentage": "2.3", "jaccard_score": 0.0006817004335614757, "number_of_representatives": "", "description": "the McMillan hotel was built in 1887, the first owner of the McMillan had killed him self in room 21 of the hotel, there have been 18 death's from 1970 till 2003 when the hotel closed down. the hotel was first call the Vivian hotel. the owner gave us a tour of the hotel and a little history of the hotel.", "cost per drink (in 2022 us$)": "2.19", "moon_upper_transit": "12:15  ST", "percentage_of_total_tribes": "1.890359168241966", "city_latitude": "45.140245", "begin_civil_twilight": "03:42  ST", "resident_population": "", "state_y": "WI", "sun_upper_transit": "11:59  ST", "state_abbrev": "WI", "binge drinking (%)": "25.8", "resident_population_density_rank": "", "adult_35plus death percentage": "86.1", "percent_change_in_resident_population": "", "simple assault": "", "male death percentage": "68.4", "latitude_x": "45.1658267", "resident_population_density": "", "usgs_region": "Midwest", "curphase": "New Moon", "city_sunrise": "", "state_x": "Wisconsin", "taxpayer cost": "4453000000.0", "hp_day": "1887/07/01", "moonset": "19:50  ST", "visual_evidence": "False", "witness_count": "18", "latitude_y": "43.0731", "longitude": "-89.1458237", "time_of_day": "Unknown", "number_of_tribes": "10.0", "sunset": "19:40  ST", "median binges monthly": "1.7", "country": "United States", "city_longitude": "-89.15233529999999", "quarter": "3", "chronic death percentage": "63.2", "rape/sexual assault": "", "robbery": ""}