{"moonrise": "12:54  DT", "event_type": "Unknown", "apparition_type": "Unknown", "number_of_representatives": "15.0", "longitude_y": "-84.5555", "longitude_x": "-84.7839364", "fracillum": "42%", "change_in_number_of_representatives": "-1.0", "median drinks per binge": "5.6", "year": "2007", "timezone": "-5.0", "personal theft/larceny": "13.0", "id": "21fc5551-8eca-44e4-8a17-160f1d72e29f", "sunrise": "06:00  DT", "inflation adjusted cost": "11018000000.0", "city": "Cheboygan", "top 25% monthly binges": "4.3", "annual deaths (excessive alcohol)": "4548.0", "end_civil_twilight": "21:55  DT", "city_sunset": "", "geography_type": "State", "city_x": "Cheboygan", "years of potential life lost": "115890.0", "audio_evidence": "False", "average_apportionment_population_per_representative": "663722.0", "state": "Michigan", "state.1": "MI", "death rate per capita": "2216.0", "latitude": "45.552789", "top 25% median drinks per binge": "7.9", "death rate increase (%)": "40.2", "location": "Pellston", "resident_population_density": "175.8", "jaccard_score": 0.0008453085376162299, "description": "January 2007 has been removed", "cost per drink (in 2022 us$)": "2.84", "moon_upper_transit": "19:14  DT", "aggravated assault": "86.0", "percentage_of_total_tribes": "2.2684310018903595", "resident_population": "9938444.0", "begin_civil_twilight": "05:25  DT", "city_latitude": "45.64695630000001", "state_y": "MI", "sun_upper_transit": "13:40  DT", "state_abbrev": "MI", "binge drinking (%)": "19.8", "resident_population_density_rank": "17.0", "adult_35plus death percentage": "84.44", "percent_change_in_resident_population": "6.9", "simple assault": "338.0", "male death percentage": "67.9", "latitude_x": "45.552789", "under 21 death percentage": "2.57", "usgs_region": "Midwest", "quarter": "1", "city_sunrise": "", "state_x": "Michigan", "taxpayer cost": "8162000000.0", "hp_day": "2007/01/01", "moonset": "01:05  DT", "visual_evidence": "False", "witness_count": "1", "latitude_y": "42.7335", "longitude": "-84.7839364", "time_of_day": "Unknown", "number_of_tribes": "12.0", "sunset": "21:20  DT", "median binges monthly": "1.8", "country": "United States", "city_longitude": "-84.4744795", "curphase": "Waxing Crescent", "chronic death percentage": "59.6", "rape/sexual assault": "24.0", "robbery": "53.0"}