{"moonrise": "09:26  ST", "event_type": "Paranormal & Supernatural Deaths", "apparition_type": "Misty Figure", "state.1": "WI", "moon_upper_transit": "16:05  ST", "longitude_x": "-88.0897021", "fracillum": "25%", "change_in_number_of_representatives": "", "year": "1863", "timezone": "-6.0", "personal theft/larceny": "", "id": "b05a8465-fbf6-4c76-b5a1-ef761888d620", "sunrise": "04:18  ST", "inflation adjusted cost": "6011000000.0", "city": "Greenbush", "male death percentage": "68.4", "top 25% monthly binges": "3.8", "visual_evidence": "False", "end_civil_twilight": "20:16  ST", "city_sunset": "", "geography_type": "", "city_x": "Greenbush", "years of potential life lost": "64214.0", "audio_evidence": "True", "average_apportionment_population_per_representative": "", "state": "Wisconsin", "death rate per capita": "2223.0", "latitude": "43.7820705", "top 25% median drinks per binge": "7.5", "death rate increase (%)": "51.4", "location": "Old Wade House", "under 21 death percentage": "2.3", "jaccard_score": 0.0007226024595751643, "number_of_representatives": "", "description": "This historical site, once a stop for the stagecoaches traveling through, has for years spoken to the tour guides. Whether encouraging guides down the steps of the back bedroom with a feeling of someone pushing, or when heard scuffing around at the butternut house as they make their beds, there is a gentle haunting experience here.", "cost per drink (in 2022 us$)": "2.19", "longitude_y": "-89.4012", "aggravated assault": "", "percentage_of_total_tribes": "1.890359168241966", "city_latitude": "43.77666019999999", "begin_civil_twilight": "03:42  ST", "resident_population": "", "state_y": "WI", "sun_upper_transit": "11:59  ST", "state_abbrev": "WI", "binge drinking (%)": "25.8", "resident_population_density_rank": "", "adult_35plus death percentage": "86.1", "percent_change_in_resident_population": "", "simple assault": "", "latitude_y": "43.0731", "latitude_x": "43.7820705", "resident_population_density": "", "median binges monthly": "1.7", "usgs_region": "Midwest", "curphase": "Waxing Crescent", "city_sunrise": "", "state_x": "Wisconsin", "taxpayer cost": "4453000000.0", "hp_day": "1863/07/15", "moonset": "22:34  ST", "annual deaths (excessive alcohol)": "2651.0", "witness_count": "2", "median drinks per binge": "5.5", "longitude": "-88.0897021", "time_of_day": "Unknown", "number_of_tribes": "10.0", "sunset": "19:40  ST", "robbery": "", "country": "United States", "city_longitude": "-88.0839854", "quarter": "3", "chronic death percentage": "63.2", "rape/sexual assault": ""}